LICENSE
README.md
setup.py
twitivity.py
twitivity.egg-info/PKG-INFO
twitivity.egg-info/SOURCES.txt
twitivity.egg-info/dependency_links.txt
twitivity.egg-info/requires.txt
twitivity.egg-info/top_level.txt