Metadata-Version: 2.1
Name: twitivity
Version: 0.3.5
Summary: Twitter Accounts Activity API Client Library for Python
Home-page: https://github.com/saadmanrafat/twitivity
Author: Saadman Rafat
Author-email: saadmanhere@gmail.com
License: MIT
Platform: UNKNOWN
Classifier: License :: OSI Approved :: MIT License
Classifier: Programming Language :: Python
Classifier: Programming Language :: Python :: 3.6
Classifier: Programming Language :: Python :: 3.7
Classifier: Programming Language :: Python :: 3.8
Classifier: Programming Language :: Python :: Implementation :: CPython
Classifier: Programming Language :: Python :: Implementation :: PyPy
Requires-Python: >=3.6.0
License-File: LICENSE
